afir_sdk/__init__.py
afir_sdk/client.py
afir_sdk/config.py
afir_sdk/middleware/__init__.py
afir_sdk/middleware/fastapi.py
afir_sdk-0.1.0.dist-info/METADATA
afir_sdk-0.1.0.dist-info/WHEEL
afir_sdk-0.1.0.dist-info/RECORD
