Metadata-Version: 2.4
Name: afir-sdk
Version: 0.1.0
Summary: Python SDK for API Failure Recorder - Track and monitor API failures
Project-URL: Homepage, https://github.com/api-failure-recorder/afir-sdk
Project-URL: Documentation, https://github.com/api-failure-recorder/afir-sdk#readme
Author: API Failure Recorder Team
License-Expression: MIT
Keywords: api,failures,incidents,monitoring,observability
Classifier: Development Status :: 4 - Beta
Classifier: Intended Audience :: Developers
Classifier: License :: OSI Approved :: MIT License
Classifier: Programming Language :: Python :: 3
Classifier: Programming Language :: Python :: 3.8
Classifier: Programming Language :: Python :: 3.9
Classifier: Programming Language :: Python :: 3.10
Classifier: Programming Language :: Python :: 3.11
Classifier: Programming Language :: Python :: 3.12
Requires-Python: >=3.8
Requires-Dist: httpx>=0.25.0
Provides-Extra: all
Requires-Dist: fastapi; extra == 'all'
Requires-Dist: flask; extra == 'all'
Provides-Extra: fastapi
Requires-Dist: fastapi; extra == 'fastapi'
Provides-Extra: flask
Requires-Dist: flask; extra == 'flask'
